setup.py
inkycal/__init__.py
inkycal/main.py
inkycal.egg-info/PKG-INFO
inkycal.egg-info/SOURCES.txt
inkycal.egg-info/dependency_links.txt
inkycal.egg-info/requires.txt
inkycal.egg-info/top_level.txt