Metadata-Version: 1.1
Name: inkycal
Version: 2.0.0b0
Summary: Python3 software for syncing icalendar events, weather and news on selected E-Paper displays
Home-page: https://github.com/aceisace/Inky-Calendar
Author: aceisace
Author-email: aceisace63@yahoo.com
License: UNKNOWN
Platform: UNKNOWN
Classifier: Development Status :: 3 - Alpha
Classifier: License :: OSI Approved :: GNU General Public License v3 (GPLv3)
Classifier: Intended Audience :: Education
Classifier: Programming Language :: Python :: 3 :: Only
